demo/__init__.py
demo/config.py
demo/extractor/__init__.py
demo/extractor/baidu_extractor.py
demo/extractor/demo_extractor.py
demo/spider/__init__.py
demo/spider/config.py
demo/spider/demo_spider.py
demo/spider/get_header_func.py
demo/spider/html_py3_3.txt
demo/spider/log.txt
demo/spider/mum_create_html.py
demo/store/__init__.py
demo/store/py_store_mysql_pool.py
download_center/__init__.py
download_center/requirements.txt
download_center/new_spider/__init__.py
download_center/new_spider/downloader/__init__.py
download_center/new_spider/downloader/config.py
download_center/new_spider/downloader/downloader.py
download_center/new_spider/downloader/html_capture.py
download_center/new_spider/downloader/html_downloader.py
download_center/new_spider/downloader/html_local_downloader.py
download_center/new_spider/downloader/html_render.py
download_center/new_spider/spider/__init__.py
download_center/new_spider/spider/basespider.py
download_center/new_spider/spider/spider.py
download_center/new_spider/util/__init__.py
download_center/new_spider/util/ua_mobile_list.txt
download_center/new_spider/util/ua_pc_list.txt
download_center/new_spider/util/ua_spider_list.txt
download_center/new_spider/util/util_md5.py
download_center/new_spider/util/util_ping.py
download_center/new_spider/util/util_url.py
download_center/new_spider/util/util_useragent.py
download_center/store/__init__.py
download_center/store/baidu_cookies.py
download_center/store/config.py
download_center/store/py_store_mysql.py
download_center/store/py_store_mysql_pool.py
download_center/store/store_cache.py
download_center/store/store_es.py
download_center/store/store_es_v2.py
download_center/store/store_file.py
download_center/store/store_mongo.py
download_center/store/store_mysql.py
download_center/store/store_mysql_pool.py
download_center/store/store_oss.py
download_center/util/__init__.py
download_center/util/py_util_basestore.py
download_center/util/util_log.py
download_center/util/util_log_v2.py
wd_download_center-5.3.1.dist-info/METADATA
wd_download_center-5.3.1.dist-info/WHEEL
wd_download_center-5.3.1.dist-info/top_level.txt
wd_download_center-5.3.1.dist-info/RECORD
