Metadata-Version: 2.1
Name: wd-download-center
Version: 5.3.1
Summary: spider framework for winndoo.
Home-page: http://git.winndoo.cn:82/python/download_center/downloader_client.git
Author: Welcome#1
Author-email: baozhu.zhang@winndoo.com
License: MIT
Platform: UNKNOWN
Classifier: License :: OSI Approved :: MIT License
Classifier: Programming Language :: Python
Classifier: Programming Language :: Python :: 3
Classifier: Programming Language :: Python :: 3.6
Classifier: Programming Language :: Python :: Implementation :: CPython
Classifier: Programming Language :: Python :: Implementation :: PyPy
Requires-Python: >=3.6.0
Requires-Dist: pymongo
Requires-Dist: oss2
Requires-Dist: redis
Requires-Dist: DBUtils
Requires-Dist: elasticsearch
Requires-Dist: flask
Requires-Dist: objgraph
Requires-Dist: lxml
Requires-Dist: cssselect
Requires-Dist: prettytable
Requires-Dist: pymysql
Requires-Dist: beautifulsoup4
